gnome_sleep.py
gnome_sleep-0.1.0.dist-info/METADATA
gnome_sleep-0.1.0.dist-info/WHEEL
gnome_sleep-0.1.0.dist-info/top_level.txt
gnome_sleep-0.1.0.dist-info/RECORD
